CHANGES.rst
MANIFEST.in
README.md
README.rst
setup.py
bin/browse
model/__init__.py
model/data.py
model/setting.py
task/__init__.py
task/audio/__init__.py
task/audio/audiospider.py
task/audio/spiderMengfou.py
task/test/__init__.py
task/test/spiderTest.py
task/test/testspider.py
webcrawl/__init__.py
webcrawl/aboutfile.py
webcrawl/atlas.py
webcrawl/character.py
webcrawl/daemon.py
webcrawl/exception.py
webcrawl/lxmlclean.py
webcrawl/prettyprint.py
webcrawl/request.py
webcrawl/rsa.py
webcrawl/spider.py
webcrawl/task.py
webcrawl/urlkit.py
webcrawl/urlparse.py
webcrawl.egg-info/PKG-INFO
webcrawl.egg-info/SOURCES.txt
webcrawl.egg-info/dependency_links.txt
webcrawl.egg-info/requires.txt
webcrawl.egg-info/top_level.txt
webcrawl/queue/__init__.py
webcrawl/queue/beanstalkd.py
webcrawl/queue/local.py
webcrawl/queue/mongo.py
webcrawl/queue/redis.py
webcrawl/queue/lib/__init__.py
webcrawl/queue/lib/queue.py
webcrawl/test/__init__.py
webcrawl/test/run.py