Metadata-Version: 1.0
Name: webcrawl
Version: 1.1.2
Summary: wecatch webcrawl
Home-page: https://github.com/listen-lavender/webcrawl
Author: haokuan
Author-email: jingdaohao@gmail.com
License: UNKNOWN
Keywords: wecatch >
Platform: UNKNOWN
